examples/all_basic_types.py
examples/auth_example.py
examples/basic_division.py
examples/dynamic_dropdowns.py
examples/enum_dropdowns.py
examples/file_return.py
examples/file_uploads.py
examples/generate_qr.py
examples/group_funcs.py
examples/image_return.py
examples/lists.py
examples/lists_constraints.py
examples/multiple_func.py
examples/multiple_returns.py
examples/numeric_constraints.py
examples/numpy_return.py
examples/optional_advanced.py
examples/pandas_return.py
examples/pdf_merger.py
examples/plot_return.py
examples/polars_example.py
examples/restart_service.py
examples/safe_division.py
examples/special_inputs.py
examples/string_constraints.py
examples/table_return.py
func_to_web/__init__.py
func_to_web/analyze_function.py
func_to_web/auth.py
func_to_web/build_form_fields.py
func_to_web/check_return_is_table.py
func_to_web/config.py
func_to_web/file_handler.py
func_to_web/process_result.py
func_to_web/routes.py
func_to_web/server.py
func_to_web/types.py
func_to_web/validate_params.py
func_to_web/templates/form.html
func_to_web/templates/index.html
func_to_web/templates/login.html
func_to_web/templates/static/builders.js
func_to_web/templates/static/main.js
func_to_web/templates/static/styles.css
func_to_web/templates/static/utils.js
func_to_web/templates/static/validators.js
func_to_web-0.9.13.dist-info/licenses/LICENSE
tests/test_analyze.py
tests/test_build_form.py
tests/test_validate.py
func_to_web-0.9.13.dist-info/METADATA
func_to_web-0.9.13.dist-info/WHEEL
func_to_web-0.9.13.dist-info/top_level.txt
func_to_web-0.9.13.dist-info/RECORD
