Metadata-Version: 2.4
Name: func-to-web
Version: 0.9.13
Summary: Transform any Python function into a web interface automatically
Author: Beltrán Offerrall
Project-URL: Homepage, https://github.com/offerrall/FuncToWeb
Project-URL: Repository, https://github.com/offerrall/FuncToWeb
Requires-Python: >=3.10
License-File: LICENSE
Requires-Dist: fastapi
Requires-Dist: uvicorn
Requires-Dist: pydantic
Requires-Dist: jinja2
Requires-Dist: python-multipart
Requires-Dist: itsdangerous
Dynamic: license-file
